codeweaver/__init__.py
codeweaver/_version.py
codeweaver/daemon.py
codeweaver/exceptions.py
codeweaver/main.py
codeweaver/py.typed
codeweaver/agent_api/__init__.py
codeweaver/agent_api/find_code/ARCHITECTURE.md
codeweaver/agent_api/find_code/README.md
codeweaver/agent_api/find_code/__init__.py
codeweaver/agent_api/find_code/conversion.py
codeweaver/agent_api/find_code/filters.py
codeweaver/agent_api/find_code/intent.py
codeweaver/agent_api/find_code/pipeline.py
codeweaver/agent_api/find_code/response.py
codeweaver/agent_api/find_code/results.py
codeweaver/agent_api/find_code/scoring.py
codeweaver/agent_api/find_code/types.py
codeweaver/cli/__init__.py
codeweaver/cli/__main__.py
codeweaver/cli/utils.py
codeweaver/cli/commands/__init__.py
codeweaver/cli/commands/config.py
codeweaver/cli/commands/context.py
codeweaver/cli/commands/doctor.py
codeweaver/cli/commands/index.py
codeweaver/cli/commands/init.py
codeweaver/cli/commands/list.py
codeweaver/cli/commands/search.py
codeweaver/cli/commands/server.py
codeweaver/cli/commands/start.py
codeweaver/cli/commands/status.py
codeweaver/cli/commands/stop.py
codeweaver/cli/ui/__init__.py
codeweaver/cli/ui/error_handler.py
codeweaver/cli/ui/status_display.py
codeweaver/common/__init__.py
codeweaver/common/logging.py
codeweaver/common/statistics.py
codeweaver/common/types.py
codeweaver/common/registry/__init__.py
codeweaver/common/registry/models.py
codeweaver/common/registry/provider.py
codeweaver/common/registry/services.py
codeweaver/common/registry/types.py
codeweaver/common/registry/utils.py
codeweaver/common/telemetry/README.md
codeweaver/common/telemetry/__init__.py
codeweaver/common/telemetry/client.py
codeweaver/common/telemetry/events.py
codeweaver/common/telemetry/utils.py
codeweaver/common/utils/__init__.py
codeweaver/common/utils/checks.py
codeweaver/common/utils/git.py
codeweaver/common/utils/introspect.py
codeweaver/common/utils/lazy_importer.py
codeweaver/common/utils/normalize.py
codeweaver/common/utils/procs.py
code_weaver-0.1.0a5.dist-info/METADATA
code_weaver-0.1.0a5.dist-info/WHEEL
code_weaver-0.1.0a5.dist-info/entry_points.txt
code_weaver-0.1.0a5.dist-info/licenses/LICENSE-Apache-2.0
code_weaver-0.1.0a5.dist-info/licenses/LICENSE-MIT
code_weaver-0.1.0a5.dist-info/RECORD
