Metadata-Version: 2.4
Name: code-weaver
Version: 0.1.0a5
Summary: Extensible MCP server for semantic code search with plugin architecture supporting multiple embedding providers, vector databases, and data sources.
Project-URL: Changelog, https://github.com/knitli/codeweaver/blob/main/CHANGELOG.md
Project-URL: Homepage, https://knitli.com
Project-URL: Issues, https://github.com/knitli/codeweaver/issues
Project-URL: Repository, https://github.com/knitli/codeweaver
Author: Knitli Inc.
Author-email: Adam Poulemanos <adam@knit.li>
License: MIT OR Apache-2.0
License-File: LICENSE-Apache-2.0
License-File: LICENSE-MIT
Keywords: agents,ai,anthropic,artificial intelligence,ast-grep,azure,bedrock,claude,code analysis,code embeddings,code indexing,code intelligence,code search,code understanding,codebase,codebase analysis,codebase management,cohere,docarray,embedding,embeddings,extensible,fastembed,fastmcp,framework,genai,google,grok,groq,huggingface,hybrid search,information retrieval,large language models,llama,llms,mcp,mcp protocol,mcp server,mistral,model context protocol,natural language processing,nlp,opena
Classifier: Development Status :: 3 - Alpha
Classifier: Environment :: Console
Classifier: Intended Audience :: Developers
Classifier: Intended Audience :: Information Technology
Classifier: License :: OSI Approved :: Apache Software License
Classifier: License :: OSI Approved :: MIT License
Classifier: Natural Language :: English
Classifier: Operating System :: OS Independent
Classifier: Programming Language :: Python :: 3 :: Only
Classifier: Programming Language :: Python :: 3.12
Classifier: Programming Language :: Python :: 3.13
Classifier: Programming Language :: Python :: 3.14
Classifier: Topic :: Database
Classifier: Topic :: Database :: Database Engines/Servers
Classifier: Topic :: Scientific/Engineering :: Artificial Intelligence
Classifier: Topic :: Scientific/Engineering :: Information Analysis
Classifier: Topic :: Software Development :: Libraries :: Application Frameworks
Classifier: Topic :: Software Development :: Libraries :: Python Modules
Classifier: Topic :: Text Processing :: Indexing
Classifier: Topic :: Utilities
Classifier: Typing :: Typed
Requires-Python: >=3.12
Requires-Dist: aenum>=3.1.16
Requires-Dist: ast-grep-py>=0.40.0
Requires-Dist: blake3>=1.0.8
Requires-Dist: cyclopts>=4.2.4
Requires-Dist: fastembed>=0.7.3
Requires-Dist: fastmcp>=2.13.1
Requires-Dist: httpx[http2]>=0.28.1
Requires-Dist: mcp>=1.19.0
Requires-Dist: numpy>=2.3.5
Requires-Dist: posthog>=7.0.1
Requires-Dist: psutil>=7.1.3
Requires-Dist: py-cpuinfo>=9.0.0
Requires-Dist: pydantic-ai>=1.20.0
Requires-Dist: pydantic-graph>=1.20.0
Requires-Dist: pydantic-settings[toml,yaml]>=2.12.0
Requires-Dist: pydantic>=2.12.4
Requires-Dist: qdrant-client>=1.16.1
Requires-Dist: rich>=14.2.0
Requires-Dist: rignore>=0.7.6
Requires-Dist: tenacity>=9.1.2
Requires-Dist: textcase>=0.4.5
Requires-Dist: tiktoken>=0.12.0
Requires-Dist: tokenizers>=0.22.1
Requires-Dist: tomli-w>=1.2.0
Requires-Dist: typing-extensions>=4.15.0
Requires-Dist: uuid7>=0.1.0; python_version < '3.14'
Requires-Dist: uvicorn[standard]>=0.38.0
Requires-Dist: uvloop>=0.22.1; platform_python_implementation == 'CPython' and platform_system != 'Windows'
Requires-Dist: voyageai>=0.3.5
Requires-Dist: watchfiles>=1.1.1
Provides-Extra: auth-eunomia
Requires-Dist: eunomia-mcp; extra == 'auth-eunomia'
Provides-Extra: auth-permitio
Requires-Dist: permit-fastmcp; extra == 'auth-permitio'
Provides-Extra: aws-secrets-manager
Requires-Dist: pydantic-settings[aws-secrets-manager,toml,yaml]; extra == 'aws-secrets-manager'
Provides-Extra: azure-key-vault
Requires-Dist: pydantic-settings[azure-key-vault,toml,yaml]; extra == 'azure-key-vault'
Provides-Extra: full
Requires-Dist: eunomia-mcp; extra == 'full'
Requires-Dist: permit-fastmcp; extra == 'full'
Requires-Dist: pydantic-settings[aws-secrets-manager,azure-key-vault,gcp-secret-manager,toml,yaml]; extra == 'full'
Requires-Dist: sentence-transformers>=5.1.2; extra == 'full'
Provides-Extra: full-gpu
Requires-Dist: eunomia-mcp; extra == 'full-gpu'
Requires-Dist: fastembed-gpu; extra == 'full-gpu'
Requires-Dist: permit-fastmcp; extra == 'full-gpu'
Requires-Dist: pydantic-settings[aws-secrets-manager,azure-key-vault,gcp-secret-manager,toml,yaml]; extra == 'full-gpu'
Provides-Extra: gcp-secret-manager
Requires-Dist: pydantic-settings[gcp-secret-manager,toml,yaml]; extra == 'gcp-secret-manager'
Provides-Extra: gpu-support
Requires-Dist: fastembed-gpu; extra == 'gpu-support'
Provides-Extra: provider-anthropic
Requires-Dist: pydantic-ai-slim[anthropic]; extra == 'provider-anthropic'
Provides-Extra: provider-bedrock
Requires-Dist: pydantic-ai-slim[bedrock]; extra == 'provider-bedrock'
Provides-Extra: provider-cohere
Requires-Dist: pydantic-ai-slim[cohere]; extra == 'provider-cohere'
Provides-Extra: provider-fastembed
Requires-Dist: fastembed; extra == 'provider-fastembed'
Requires-Dist: py-cpuinfo; extra == 'provider-fastembed'
Provides-Extra: provider-fastembed-gpu
Requires-Dist: fastembed-gpu; extra == 'provider-fastembed-gpu'
Requires-Dist: py-cpuinfo; extra == 'provider-fastembed-gpu'
Provides-Extra: provider-google
Requires-Dist: pydantic-ai-slim[google]; extra == 'provider-google'
Provides-Extra: provider-groq
Requires-Dist: pydantic-ai-slim[groq]; extra == 'provider-groq'
Provides-Extra: provider-huggingface
Requires-Dist: pydantic-ai-slim[huggingface]; extra == 'provider-huggingface'
Provides-Extra: provider-in-memory
Requires-Dist: qdrant-client; extra == 'provider-in-memory'
Requires-Dist: tokenizers; extra == 'provider-in-memory'
Provides-Extra: provider-mistral
Requires-Dist: pydantic-ai-slim[mistral]; extra == 'provider-mistral'
Provides-Extra: provider-openai
Requires-Dist: pydantic-ai-slim[openai]; extra == 'provider-openai'
Provides-Extra: provider-qdrant
Requires-Dist: qdrant-client; extra == 'provider-qdrant'
Provides-Extra: provider-sentence-transformers
Requires-Dist: py-cpuinfo; extra == 'provider-sentence-transformers'
Requires-Dist: sentence-transformers; extra == 'provider-sentence-transformers'
Provides-Extra: provider-voyageai
Requires-Dist: voyageai; extra == 'provider-voyageai'
Provides-Extra: recommended-local-only
Requires-Dist: fastembed; extra == 'recommended-local-only'
Requires-Dist: sentence-transformers; extra == 'recommended-local-only'
Requires-Dist: tokenizers; extra == 'recommended-local-only'
Provides-Extra: source-duckduckgo
Requires-Dist: pydantic-ai-slim[duckduckgo]; extra == 'source-duckduckgo'
Provides-Extra: source-tavily
Requires-Dist: pydantic-ai-slim[tavily]; extra == 'source-tavily'
